odoo/addons/website_partner_form/README.rst
odoo/addons/website_partner_form/__init__.py
odoo/addons/website_partner_form/__manifest__.py
odoo/addons/website_partner_form/i18n/fr.po
odoo/addons/website_partner_form/i18n/it.po
odoo/addons/website_partner_form/i18n/website_partner_form.pot
odoo/addons/website_partner_form/readme/CONTRIBUTORS.md
odoo/addons/website_partner_form/readme/DESCRIPTION.md
odoo/addons/website_partner_form/static/description/icon.png
odoo/addons/website_partner_form/static/description/index.html
odoo/addons/website_partner_form/static/description/res_partner_form.png
odoo/addons/website_partner_form/views/view_res_partner.xml
odoo_addon_website_partner_form-18.0.1.0.0.4.dist-info/METADATA
odoo_addon_website_partner_form-18.0.1.0.0.4.dist-info/WHEEL
odoo_addon_website_partner_form-18.0.1.0.0.4.dist-info/top_level.txt
odoo_addon_website_partner_form-18.0.1.0.0.4.dist-info/RECORD
